[
   {
      "Data": "7 de Outubro de 2018",
      "NumeroDoPremio": "1º Prêmio",
      "Premio": "5 mil reais - valor líquido",
      "Dezenas": [
         "29",
         "13",
         "10",
         "31",
         "07",
         "41",
         "06",
         "24",
         "40",
         "49",
         "54",
         "44",
         "11",
         "23",
         "51",
         "46",
         "26",
         "37",
         "53",
         "17",
         "21",
         "02",
         "04",
         "33",
         "42",
         "19",
         "20",
         "14",
         "28",
         "57",
         "39",
         "36",
         "15",
         "50",
         "18",
         "55",
         "43",
         "38"
      ],
      "Contemplados": [
         {
            "Numero": "1",
            "Certificado": "397.053",
            "Nome": "CARLOS ROBERTO INOCÊNCIO",
            "Endereço": "RUA DUQUE DE CAXIAS, 51",
            "Bairro": "PQ. SÃO MIGUEL",
            "Cidade": "PIQUETE",
            "PontoDeVenda": "PONTO DA SORTE - CALÇADÃO LORENA"
         },
         {
            "Numero": "2",
            "Certificado": "454.166",
            "Nome": "LEILA APARECIDA DOS SANTOS",
            "Endereço": "RUA BENEDITO F. DE PAULA, 91",
            "Bairro": "MASSAGUAÇU",
            "Cidade": "CARAGUATATUBA ",
            "PontoDeVenda": "CABINE DA NILCE DO CENTRO"
         },
         {
            "Numero": "3",
            "Certificado": "485.660",
            "Nome": "ORLANDO REIS DA CRUZ",
            "Endereço": "AVENIDA CONDERELA, 1911",
            "Bairro": "GURILÂNDIA",
            "Cidade": "TAUBATÉ ",
            "PontoDeVenda": "BAR BRAZIL"
         }
      ]
   },
   {
      "Data": "7 de Outubro de 2018",
      "NumeroDoPremio": "2º Prêmio",
      "Premio": "10 mil reais - valor líquido",
      "Dezenas": [
         "52",
         "20",
         "03",
         "58",
         "28",
         "48",
         "08",
         "32",
         "10",
         "38",
         "45",
         "26",
         "23",
         "16",
         "06",
         "05",
         "42",
         "56",
         "57",
         "39",
         "07",
         "43",
         "27",
         "54",
         "02",
         "34",
         "53",
         "60",
         "55",
         "04",
         "33",
         "22",
         "15",
         "17",
         "35",
         "59",
         "30"
      ],
      "Contemplados": [
         {
            "Numero": "1",
            "Certificado": "047.182",
            "Nome": "MILTON GOMES MOREIRA",
            "Endereço": "RUA ANTÔNIO MAXIMINIANO DE ANDRADE",
            "Bairro": "RESIDENCIAL UNIÃO",
            "Cidade": "SAO JOSÉ DOS CAMPOS",
            "PontoDeVenda": "null"
         },
         {
            "Numero": "2",
            "Certificado": "341.616",
            "Nome": "GABRIEL MOREIRA LIMA SANTOS",
            "Endereço": "RUA DONA AMÉLIA PANTALEÃO, 205 APTO 103",
            "Bairro": "VILA PANTALEÃO",
            "Cidade": "CAÇAPAVA ",
            "PontoDeVenda": "BANCA DO CLAUDIO"
         }
      ]
   },
   {
      "Data": "7 de Outubro de 2018",
      "NumeroDoPremio": "3º Prêmio",
      "Premio": "15 mil reais - valor líquido",
      "Dezenas": [
         "15",
         "40",
         "02",
         "01",
         "04",
         "22",
         "12",
         "57",
         "13",
         "49",
         "50",
         "32",
         "06",
         "38",
         "08",
         "53",
         "17",
         "03",
         "29",
         "44",
         "19",
         "35",
         "47",
         "20",
         "18",
         "21",
         "25",
         "59",
         "37",
         "28",
         "46",
         "45",
         "09",
         "16",
         "31",
         "27",
         "24"
      ],
      "Contemplados": [
         {
            "Numero": "1",
            "Certificado": "397.076",
            "Nome": "CLÁUDIA SILVA",
            "Endereço": "RUA MÁRIO PRUDENTE DE AQUINO, 372",
            "Bairro": "BAIRRO DA CRUZ",
            "Cidade": "LORENA",
            "PontoDeVenda": "PONTO DA SORTE - CALÇADÃO LORENA"
         },
         {
            "Numero": "2",
            "Certificado": "472.068",
            "Nome": "MARIA JOSÉ CORRÊA COSTA",
            "Endereço": "RUA GREGÓRIO GUREVICH, 111",
            "Bairro": "JD. DIAMANTE",
            "Cidade": "SÃO JOSÉ DOS CAMPOS",
            "PontoDeVenda": "BANCA DO CLÁUDIO SANTOS"
         }
      ]
   },
   {
      "Data": "7 de Outubro de 2018",
      "NumeroDoPremio": "4º Prêmio",
      "Premio": "500 mil reais - valor líquido",
      "Dezenas": [
         "21",
         "17",
         "50",
         "15",
         "08",
         "05",
         "18",
         "19",
         "54",
         "42",
         "24",
         "38",
         "01",
         "30",
         "37",
         "16",
         "60",
         "45",
         "11",
         "36",
         "47",
         "33",
         "07",
         "02",
         "48",
         "29",
         "35",
         "51",
         "23",
         "46",
         "20",
         "04",
         "40",
         "22",
         "56",
         "27"
      ],
      "Contemplados": [
         {
            "Numero": "1",
            "Certificado": "059.352",
            "Nome": "JOSÉ FERREIRA DA SILVA JÚNIOR",
            "Endereço": "RUA LUZIA MACHADO JALDÃO, 49",
            "Bairro": "VILA ITA 2",
            "Cidade": "JACAREÍ",
            "PontoDeVenda": "BAR DO RONALDO"
         }
      ]
   }
]